LICENSE
README.md
pyproject.toml
jararaca/__init__.py
jararaca/__main__.py
jararaca/broker_backend/__init__.py
jararaca/broker_backend/mapper.py
jararaca/broker_backend/redis_broker_backend.py
jararaca/cli.py
jararaca/common/__init__.py
jararaca/core/__init__.py
jararaca/core/providers.py
jararaca/core/uow.py
jararaca/di.py
jararaca/files/entity.py.mako
jararaca/lifecycle.py
jararaca/messagebus/__init__.py
jararaca/messagebus/bus_message_controller.py
jararaca/messagebus/consumers/__init__.py
jararaca/messagebus/decorators.py
jararaca/messagebus/implicit_headers.py
jararaca/messagebus/interceptors/__init__.py
jararaca/messagebus/interceptors/aiopika_publisher_interceptor.py
jararaca/messagebus/interceptors/publisher_interceptor.py
jararaca/messagebus/message.py
jararaca/messagebus/publisher.py
jararaca/messagebus/worker.py
jararaca/microservice.py
jararaca/observability/constants.py
jararaca/observability/decorators.py
jararaca/observability/fastapi_exception_handler.py
jararaca/observability/hooks.py
jararaca/observability/interceptor.py
jararaca/observability/providers/__init__.py
jararaca/observability/providers/otel.py
jararaca/persistence/base.py
jararaca/persistence/exports.py
jararaca/persistence/interceptors/__init__.py
jararaca/persistence/interceptors/aiosqa_interceptor.py
jararaca/persistence/interceptors/constants.py
jararaca/persistence/interceptors/decorators.py
jararaca/persistence/session.py
jararaca/persistence/sort_filter.py
jararaca/persistence/utilities.py
jararaca/presentation/__init__.py
jararaca/presentation/decorators.py
jararaca/presentation/hooks.py
jararaca/presentation/http_microservice.py
jararaca/presentation/server.py
jararaca/presentation/websocket/__init__.py
jararaca/presentation/websocket/base_types.py
jararaca/presentation/websocket/context.py
jararaca/presentation/websocket/decorators.py
jararaca/presentation/websocket/redis.py
jararaca/presentation/websocket/types.py
jararaca/presentation/websocket/websocket_interceptor.py
jararaca-0.3.42.dist-info/LICENSE
jararaca-0.3.42.dist-info/LICENSES/GPL-3.0-or-later.txt
jararaca-0.3.42.dist-info/METADATA
jararaca-0.3.42.dist-info/WHEEL
jararaca-0.3.42.dist-info/entry_points.txt
jararaca-0.3.42.dist-info/RECORD
