Metadata-Version: 2.1
Name: jararaca
Version: 0.3.42
Summary: A simple and fast API framework for Python
Home-page: https://github.com/LuscasLeo/jararaca
License: GPL-3.0-or-later
Author: Lucas S
Author-email: me@luscasleo.dev
Requires-Python: >=3.11,<4.0
Classifier: License :: OSI Approved :: GNU General Public License v3 or later (GPLv3+)
Classifier: Programming Language :: Python :: 3
Classifier: Programming Language :: Python :: 3.11
Classifier: Programming Language :: Python :: 3.12
Provides-Extra: docs
Provides-Extra: http
Provides-Extra: opentelemetry
Provides-Extra: watch
Requires-Dist: aio-pika (>=9.4.3,<10.0.0)
Requires-Dist: croniter (>=3.0.3,<4.0.0)
Requires-Dist: fastapi (>=0.113.0,<0.114.0)
Requires-Dist: frozendict (>=2.4.6,<3.0.0)
Requires-Dist: mako (>=1.3.5,<2.0.0)
Requires-Dist: opentelemetry-api (>=1.38.0,<2.0.0) ; extra == "opentelemetry"
Requires-Dist: opentelemetry-distro (>=0.59b0,<0.60) ; extra == "opentelemetry"
Requires-Dist: opentelemetry-exporter-otlp (>=1.27.0,<2.0.0) ; extra == "opentelemetry"
Requires-Dist: opentelemetry-exporter-otlp-proto-http (>=1.27.0,<2.0.0) ; extra == "opentelemetry"
Requires-Dist: opentelemetry-sdk (>=1.38.0,<2.0.0) ; extra == "opentelemetry"
Requires-Dist: redis (>=5.0.8,<6.0.0)
Requires-Dist: sqlalchemy (>=2.0.34,<3.0.0)
Requires-Dist: types-croniter (>=3.0.3.20240731,<4.0.0.0)
Requires-Dist: types-redis (>=4.6.0.20240903,<5.0.0.0)
Requires-Dist: urllib3 (>=2.3.0,<3.0.0)
Requires-Dist: uvicorn (>=0.30.6,<0.31.0)
Requires-Dist: uvloop (>=0.20.0,<0.21.0)
Requires-Dist: watchdog (>=3.0.0,<4.0.0) ; extra == "watch"
Requires-Dist: websockets (>=13.0.1,<14.0.0)
Project-URL: Repository, https://github.com/LuscasLeo/jararaca
